sunshine_conversations_client/__init__.py
sunshine_conversations_client/api_client.py
sunshine_conversations_client/api_response.py
sunshine_conversations_client/configuration.py
sunshine_conversations_client/exceptions.py
sunshine_conversations_client/py.typed
sunshine_conversations_client/rest.py
sunshine_conversations_client/api/__init__.py
sunshine_conversations_client/api/activities_api.py
sunshine_conversations_client/api/app_keys_api.py
sunshine_conversations_client/api/apps_api.py
sunshine_conversations_client/api/attachments_api.py
sunshine_conversations_client/api/clients_api.py
sunshine_conversations_client/api/conversations_api.py
sunshine_conversations_client/api/custom_integration_api_keys_api.py
sunshine_conversations_client/api/devices_api.py
sunshine_conversations_client/api/integrations_api.py
sunshine_conversations_client/api/messages_api.py
sunshine_conversations_client/api/o_auth_endpoints_api.py
sunshine_conversations_client/api/participants_api.py
sunshine_conversations_client/api/switchboard_actions_api.py
sunshine_conversations_client/api/switchboard_integrations_api.py
sunshine_conversations_client/api/switchboards_api.py
sunshine_conversations_client/api/users_api.py
sunshine_conversations_client/api/webhooks_api.py
sunshine_conversations_client/model/__init__.py
sunshine_conversations_client/model/accept_control_body.py
sunshine_conversations_client/model/action.py
sunshine_conversations_client/model/action_subset.py
sunshine_conversations_client/model/activity.py
sunshine_conversations_client/model/activity_message.py
sunshine_conversations_client/model/activity_post.py
sunshine_conversations_client/model/activity_types.py
sunshine_conversations_client/model/android.py
sunshine_conversations_client/model/android_update.py
sunshine_conversations_client/model/api_key.py
sunshine_conversations_client/model/app.py
sunshine_conversations_client/model/app_create_body.py
sunshine_conversations_client/model/app_key.py
sunshine_conversations_client-17.0.1.dist-info/LICENSE
sunshine_conversations_client-17.0.1.dist-info/METADATA
sunshine_conversations_client-17.0.1.dist-info/WHEEL
sunshine_conversations_client-17.0.1.dist-info/top_level.txt
sunshine_conversations_client-17.0.1.dist-info/RECORD
