Metadata-Version: 2.1
Name: sunshine-conversations-client
Version: 17.0.1
Summary: Sunshine Conversations API
Home-page: 
Author: OpenAPI Generator community
Author-email: team@openapitools.org
Keywords: OpenAPI,OpenAPI-Generator,Sunshine Conversations API
License-File: LICENSE
Requires-Dist: urllib3 <3.0.0,>=1.25.3
Requires-Dist: python-dateutil >=2.8.2
Requires-Dist: pydantic >=2
Requires-Dist: typing-extensions >=4.7.1
